flask_xmlrpcre/__init__.py
flask_xmlrpcre/xmlrpcre.py
flaskext/xmlrpc.py
Flask_XML_RPC_Re-0.2.0.dist-info/LICENSE
Flask_XML_RPC_Re-0.2.0.dist-info/METADATA
Flask_XML_RPC_Re-0.2.0.dist-info/WHEEL
Flask_XML_RPC_Re-0.2.0.dist-info/top_level.txt
Flask_XML_RPC_Re-0.2.0.dist-info/RECORD
