Metadata-Version: 2.1
Name: Flask-XML-RPC-Re
Version: 0.2.0
Summary: Adds support for creating XML-RPC APIs to Flask
Home-page: https://github.com/Croydon/flask-xml-rpc-reloaded
Author: Matthew "LeafStorm" Frazier
Author-email: flask@go-dev.de
License: MIT
Keywords: XML-RPC
Platform: any
Classifier: Development Status :: 4 - Beta
Classifier: Environment :: Web Environment
Classifier: Intended Audience :: Developers
Classifier: License :: OSI Approved :: MIT License
Classifier: Operating System :: OS Independent
Classifier: Programming Language :: Python
Classifier: Topic :: Internet :: WWW/HTTP :: Dynamic Content
Classifier: Topic :: Software Development :: Libraries :: Python Modules
License-File: LICENSE
Requires-Dist: Flask
Provides-Extra: dev
Requires-Dist: sphinx ; extra == 'dev'
Provides-Extra: test
Requires-Dist: nose ; extra == 'test'
